LICENSE
README.md
pyproject.toml
.github/workflows/python-publish.yml
docs/Makefile
docs/abbrev_long.bib
docs/conf.py
docs/conf_overrides.py
docs/conf_spec.py
docs/index.rst
docs/make.bat
docs/references.bib
docs/_build/.buildinfo
docs/_build/.buildinfo.bak
docs/_build/genindex.html
docs/_build/index.html
docs/_build/objects.inv
docs/_build/py-modindex.html
docs/_build/search.html
docs/_build/searchindex.js
docs/_build/.doctrees/environment.pickle
docs/_build/.doctrees/index.doctree
docs/_build/.doctrees/api/index.doctree
docs/_build/.doctrees/api/bodycompress/BodyCompressor.__exit__.doctree
docs/_build/.doctrees/api/bodycompress/BodyCompressor.append.doctree
docs/_build/.doctrees/api/bodycompress/BodyCompressor.close.doctree
docs/_build/.doctrees/api/bodycompress/BodyCompressor.doctree
docs/_build/.doctrees/api/bodycompress/BodyDecompressor.__exit__.doctree
docs/_build/.doctrees/api/bodycompress/BodyDecompressor.__next__.doctree
docs/_build/.doctrees/api/bodycompress/BodyDecompressor.close.doctree
docs/_build/.doctrees/api/bodycompress/BodyDecompressor.doctree
docs/_build/.doctrees/api/bodycompress/index.doctree
docs/_build/_modules/index.html
docs/_build/_modules/bodycompress/bodycompress.html
docs/_build/_sources/index.rst.txt
docs/_build/_sources/api/index.rst.txt
docs/_build/_sources/api/bodycompress/BodyCompressor.__exit__.rst.txt
docs/_build/_sources/api/bodycompress/BodyCompressor.append.rst.txt
docs/_build/_sources/api/bodycompress/BodyCompressor.close.rst.txt
docs/_build/_sources/api/bodycompress/BodyCompressor.rst.txt
docs/_build/_sources/api/bodycompress/BodyDecompressor.__exit__.rst.txt
docs/_build/_sources/api/bodycompress/BodyDecompressor.__next__.rst.txt
docs/_build/_sources/api/bodycompress/BodyDecompressor.close.rst.txt
docs/_build/_sources/api/bodycompress/BodyDecompressor.rst.txt
docs/_build/_sources/api/bodycompress/index.rst.txt
docs/_build/_static/basic.css
docs/_build/_static/doctools.js
docs/_build/_static/documentation_options.js
src/bodycompress.egg-info/PKG-INFO
src/bodycompress.egg-info/SOURCES.txt
src/bodycompress.egg-info/dependency_links.txt
src/bodycompress.egg-info/requires.txt
src/bodycompress.egg-info/top_level.txt
