Metadata-Version: 2.4
Name: bodycompress
Version: 0.2.3.dev0
Summary: Tool for efficiently (de)serializing and (de)compressing nonparametric 3D human body pose and shape estimation results.
Author-email: István Sárándi <istvan.sarandi@uni-tuebingen.de>
License-Expression: MIT
Project-URL: Homepage, https://github.com/isarandi/bodycompress
Project-URL: Repository, https://github.com/isarandi/bodycompress
Project-URL: Issues, https://github.com/isarandi/bodycompress/issues
Project-URL: Author, https://istvansarandi.com
Classifier: Development Status :: 4 - Beta
Classifier: Intended Audience :: Developers
Classifier: Topic :: Software Development :: Libraries
Classifier: Programming Language :: Python
Classifier: Programming Language :: Python :: 3
Classifier: Operating System :: POSIX :: Linux
Requires-Python: >=3.8
License-File: LICENSE
Requires-Dist: numpy
Requires-Dist: scipy
Requires-Dist: msgpack_numpy
Requires-Dist: cameravision
Dynamic: license-file
